{
  "_class": "symbolInstance",
  "booleanOperation": -1,
  "do_objectID": "F50A91BE-1D34-4F5A-AEBE-472A4E3EFE50",
  "exportOptions": {
    "_class": "exportOptions",
    "do_objectID": "ACB85E66-9E19-4843-A786-7AE18623E7FE",
    "exportFormats": [
    ],
    "includedLayerIds": [
    ],
    "layerOptions": 0,
    "shouldTrim": false
  },
  "frame": {
    "_class": "rect",
    "constrainProportions": false,
    "do_objectID": "973014D1-7AE5-408C-AAF3-B0A9FA08D8BB",
    "height": 1054,
    "width": 311,
    "x": 32,
    "y": 56
  },
  "horizontalSpacing": 0,
  "isFixedToViewport": false,
  "isFlippedHorizontal": false,
  "isFlippedVertical": false,
  "isLocked": false,
  "isVisible": true,
  "layerListExpandedType": 0,
  "name": "home-page-content",
  "nameIsFixed": false,
  "overrideValues": [
  ],
  "resizingConstraint": 63,
  "resizingType": 0,
  "rotation": 0,
  "scale": 1,
  "shouldBreakMaskChain": false,
  "style": {
    "_class": "style",
    "do_objectID": "ABA43676-7DC9-49EF-A4F4-7C16A322832A",
    "endMarkerType": 0,
    "miterLimit": 10,
    "startMarkerType": 0,
    "windingRule": 1
  },
  "symbolID": "00F919E3-E63A-4FF4-9935-6F2A3CC36E01",
  "userInfo": {
    "com.animaapp.stc-sketch-plugin": {
      "kModelPropertiesKey": {
      }
    }
  },
  "verticalSpacing": 0
}